{"homebrew_version":null,"used_options":[],"unused_options":["--universal"],"built_as_bottle":true,"poured_from_bottle":true,"installed_as_dependency":true,"installed_on_request":true,"changed_files":null,"time":1495647641,"source_modified_time":1465650801,"HEAD":null,"stdlib":"libcxx","compiler":"clang","runtime_dependencies":null,"source":{"path":"/usr/local/Homebrew/Library/Taps/homebrew/homebrew-core/Formula/gettext.rb","tap":"homebrew/core","spec":"stable","versions":{"stable":"0.19.8.1","devel":null,"head":null,"version_scheme":0}}}